rang_colorpalette/__init__.py
rang_colorpalette/color.py
rang_colorpalette/palette.py
rang_colorpalette/themes.py
rang_colorpalette-0.1.0.dist-info/LICENSE
rang_colorpalette-0.1.0.dist-info/METADATA
rang_colorpalette-0.1.0.dist-info/WHEEL
rang_colorpalette-0.1.0.dist-info/RECORD
