Metadata-Version: 2.1
Name: rang-colorpalette
Version: 0.1.0
Summary: Awesome `rang_colorpalette` is a Python cli/package created with https://github.com/TezRomacH/python-package-template
Home-page: https://github.com/jptalukdar/rang_colorpalette
License: GNU GPL v3.0
Author: rang_colorpalette
Author-email: github@jyotiplaban.com
Requires-Python: >=3.9,<4.0
Classifier: Development Status :: 3 - Alpha
Classifier: Intended Audience :: Developers
Classifier: License :: OSI Approved :: GNU General Public License v3 or later (GPLv3+)
Classifier: License :: Other/Proprietary License
Classifier: Operating System :: OS Independent
Classifier: Programming Language :: Python :: 3
Classifier: Programming Language :: Python :: 3.9
Classifier: Programming Language :: Python :: 3.10
Classifier: Programming Language :: Python :: 3.11
Classifier: Programming Language :: Python :: 3
Classifier: Programming Language :: Python :: 3.9
Classifier: Topic :: Software Development :: Libraries :: Python Modules
Requires-Dist: matplotlib (>=3.6.2,<4.0.0)
Project-URL: Repository, https://github.com/jptalukdar/rang_colorpalette
